{"ENV_Online Simulation_TotalLoss": 7.374872461732205, "ENV_Online Simulation_TotalLoss_epoch0": 9.942581589435896, "ENV_Online Simulation_Right action": 0.47872965038697624, "ENV_Online Simulation_Right action_epoch0": 0.4879705953893138, "ENV_Online Simulation_Probability to choose the right action": 0.4789412346990458, "ENV_Online Simulation_Probability to choose the right action_epoch0": 0.48798345982187147, "ENV_Online Simulation_Weighted right action": 0.9995034784403645, "ENV_Online Simulation_Weighted right action_epoch0": 0.9995125004847296, "ENV_Online Simulation_Weighted probability to choose the right action:": 0.9987527955475267, "ENV_Online Simulation_Weighted probability to choose the right action:_epoch0": 0.9982481091738535, "_timestamp": 1728297758.1792095, "_runtime": 3365.260400533676, "_step": 29, "ENV_Train_TotalLoss": 1057.1649708036623, "ENV_Train_TotalLoss_epoch0": 1282.5755439899904, "ENV_Train_Right action": 0.7838374238273607, "ENV_Train_Right action_epoch0": 0.7134134413860556, "ENV_Train_Probability to choose the right action": 0.7040390410211305, "ENV_Train_Probability to choose the right action_epoch0": 0.6258088911193989, "ENV_Train_Weighted right action": 0.7838374238273607, "ENV_Train_Weighted right action_epoch0": 0.7134134413860556, "ENV_Train_Weighted probability to choose the right action:": 0.7040390410211305, "ENV_Train_Weighted probability to choose the right action:_epoch0": 0.6258088911193989, "ENV_Test_TotalLoss": 230.86857865084636, "ENV_Test_TotalLoss_epoch0": 244.09500348046416, "ENV_Test_Right action": 0.7808, "ENV_Test_Right action_epoch0": 0.773184, "ENV_Test_Probability to choose the right action": 0.7138333924641925, "ENV_Test_Probability to choose the right action_epoch0": 0.6966637477053876, "ENV_Test_Weighted right action": 0.8244743823223752, "ENV_Test_Weighted right action_epoch0": 0.8168983412365333, "ENV_Test_Weighted probability to choose the right action:": 0.7537156146649545, "ENV_Test_Weighted probability to choose the right action:_epoch0": 0.7305637925177308, "ENV_Test_proba_accuracy": 0.7138333924641928, "ENV_Test_proba_accuracy_epoch0": 0.6966637477053879, "ENV_Test_proba_accuracy_strategy_132": 0.7556860456805664, "ENV_Test_proba_accuracy_strategy_132_epoch0": 0.7286131386596801, "ENV_Test_proba_accuracy_strategy_23": 0.7147379327944893, "ENV_Test_proba_accuracy_strategy_23_epoch0": 0.6970704032610193, "ENV_Test_proba_accuracy_strategy_107": 0.8048678063727497, "ENV_Test_proba_accuracy_strategy_107_epoch0": 0.7742691907938469, "ENV_Test_proba_accuracy_strategy_43": 0.71930927267595, "ENV_Test_proba_accuracy_strategy_43_epoch0": 0.7031446611485727, "ENV_Test_proba_accuracy_strategy_17": 0.6808771130627392, "ENV_Test_proba_accuracy_strategy_17_epoch0": 0.6696115862125034, "ENV_Test_proba_accuracy_strategy_93": 0.7154554856317599, "ENV_Test_proba_accuracy_strategy_93_epoch0": 0.6993335728615323, "ENV_Test_proba_accuracy_per_mean_strategy": 0.7318222760363757, "ENV_Test_proba_accuracy_per_mean_strategy_epoch0": 0.7120070921561923, "ENV_Test_proba_accuracy_per_mean_user": 0.7225315839596654, "ENV_Test_proba_accuracy_per_mean_user_epoch0": 0.7048541187753408, "ENV_Test_proba_accuracy_per_mean_user_and_bot": 0.7537156146649548, "ENV_Test_proba_accuracy_per_mean_user_and_bot_epoch0": 0.7305637925177306, "ENV_Test_accuracy": 0.7808, "ENV_Test_accuracy_epoch0": 0.773184, "ENV_Test_accuracy_strategy_132": 0.8152974504249292, "ENV_Test_accuracy_strategy_132_epoch0": 0.8056657223796034, "ENV_Test_accuracy_strategy_23": 0.7846178704152529, "ENV_Test_accuracy_strategy_23_epoch0": 0.7784779447406689, "ENV_Test_accuracy_strategy_107": 0.8768472906403941, "ENV_Test_accuracy_strategy_107_epoch0": 0.8669950738916257, "ENV_Test_accuracy_strategy_43": 0.7881679389312977, "ENV_Test_accuracy_strategy_43_epoch0": 0.7818066157760815, "ENV_Test_accuracy_strategy_17": 0.7465970961887477, "ENV_Test_accuracy_strategy_17_epoch0": 0.7363883847549909, "ENV_Test_accuracy_strategy_93": 0.777264325323475, "ENV_Test_accuracy_strategy_93_epoch0": 0.7744916820702403, "ENV_Test_accuracy_per_mean_strategy": 0.7981319953206828, "ENV_Test_accuracy_per_mean_strategy_epoch0": 0.7906375706022017, "ENV_Test_accuracy_per_mean_user": 0.7921987000695457, "ENV_Test_accuracy_per_mean_user_epoch0": 0.7825350739206521, "ENV_Test_accuracy_per_mean_user_and_bot": 0.824474382322376, "ENV_Test_accuracy_per_mean_user_and_bot_epoch0": 0.8168983412365346, "ENV_Online Simulation_TotalLoss_epoch1": 3.7934052249875685, "ENV_Online Simulation_Right action_epoch1": 0.48535123856401474, "ENV_Online Simulation_Probability to choose the right action_epoch1": 0.48536242747074726, "ENV_Online Simulation_Weighted right action_epoch1": 0.9997187836012241, "ENV_Online Simulation_Weighted probability to choose the right action:_epoch1": 0.9993825733183446, "ENV_Train_TotalLoss_epoch1": 1118.607097101358, "ENV_Train_Right action_epoch1": 0.7706457925636008, "ENV_Train_Probability to choose the right action_epoch1": 0.6861204408439054, "ENV_Train_Weighted right action_epoch1": 0.7706457925636008, "ENV_Train_Weighted probability to choose the right action:_epoch1": 0.6861204408439054, "ENV_Test_TotalLoss_epoch1": 235.9196709933046, "ENV_Test_Right action_epoch1": 0.776064, "ENV_Test_Probability to choose the right action_epoch1": 0.7068841007856862, "ENV_Test_Weighted right action_epoch1": 0.8212036299715426, "ENV_Test_Weighted probability to choose the right action:_epoch1": 0.7456072966020738, "ENV_Test_proba_accuracy_epoch1": 0.7068841007856861, "ENV_Test_proba_accuracy_strategy_132_epoch1": 0.7472236725157677, "ENV_Test_proba_accuracy_strategy_23_epoch1": 0.7073590117613587, "ENV_Test_proba_accuracy_strategy_107_epoch1": 0.7929730836866216, "ENV_Test_proba_accuracy_strategy_43_epoch1": 0.7128617092097372, "ENV_Test_proba_accuracy_strategy_17_epoch1": 0.675687866793452, "ENV_Test_proba_accuracy_strategy_93_epoch1": 0.708316115828623, "ENV_Test_proba_accuracy_per_mean_strategy_epoch1": 0.7240702432992601, "ENV_Test_proba_accuracy_per_mean_user_epoch1": 0.7152590322260246, "ENV_Test_proba_accuracy_per_mean_user_and_bot_epoch1": 0.7456072966020727, "ENV_Test_accuracy_epoch1": 0.776064, "ENV_Test_accuracy_strategy_132_epoch1": 0.8056657223796034, "ENV_Test_accuracy_strategy_23_epoch1": 0.7810631766036517, "ENV_Test_accuracy_strategy_107_epoch1": 0.8719211822660099, "ENV_Test_accuracy_strategy_43_epoch1": 0.7849872773536896, "ENV_Test_accuracy_strategy_17_epoch1": 0.7402450090744102, "ENV_Test_accuracy_strategy_93_epoch1": 0.7781885397412199, "ENV_Test_accuracy_per_mean_strategy_epoch1": 0.7936784845697641, "ENV_Test_accuracy_per_mean_user_epoch1": 0.7856551685919737, "ENV_Test_accuracy_per_mean_user_and_bot_epoch1": 0.821203629971543, "ENV_Online Simulation_TotalLoss_epoch2": 4.829093919129597, "ENV_Online Simulation_Right action_epoch2": 0.476881033310673, "ENV_Online Simulation_Probability to choose the right action_epoch2": 0.4769320734873697, "ENV_Online Simulation_Weighted right action_epoch2": 0.9996348699224099, "ENV_Online Simulation_Weighted probability to choose the right action:_epoch2": 0.999216471646643, "ENV_Train_TotalLoss_epoch2": 1098.7777403585944, "ENV_Train_Right action_epoch2": 0.7741123846798994, "ENV_Train_Probability to choose the right action_epoch2": 0.6917746865751315, "ENV_Train_Weighted right action_epoch2": 0.7741123846798994, "ENV_Train_Weighted probability to choose the right action:_epoch2": 0.6917746865751315, "ENV_Test_TotalLoss_epoch2": 234.43430548965097, "ENV_Test_Right action_epoch2": 0.778752, "ENV_Test_Probability to choose the right action_epoch2": 0.7022250915702606, "ENV_Test_Weighted right action_epoch2": 0.8217753308379149, "ENV_Test_Weighted probability to choose the right action:_epoch2": 0.7425109736871177, "ENV_Test_proba_accuracy_epoch2": 0.7022250915702614, "ENV_Test_proba_accuracy_strategy_132_epoch2": 0.7445724681155468, "ENV_Test_proba_accuracy_strategy_23_epoch2": 0.7004845395825448, "ENV_Test_proba_accuracy_strategy_107_epoch2": 0.7940214322437995, "ENV_Test_proba_accuracy_strategy_43_epoch2": 0.710175982655361, "ENV_Test_proba_accuracy_strategy_17_epoch2": 0.6710308242728863, "ENV_Test_proba_accuracy_strategy_93_epoch2": 0.7069669720142693, "ENV_Test_proba_accuracy_per_mean_strategy_epoch2": 0.7212087031474014, "ENV_Test_proba_accuracy_per_mean_user_epoch2": 0.7114514661185923, "ENV_Test_proba_accuracy_per_mean_user_and_bot_epoch2": 0.7425109736871178, "ENV_Test_accuracy_epoch2": 0.778752, "ENV_Test_accuracy_strategy_132_epoch2": 0.8084985835694051, "ENV_Test_accuracy_strategy_23_epoch2": 0.7813863305865245, "ENV_Test_accuracy_strategy_107_epoch2": 0.8702791461412152, "ENV_Test_accuracy_strategy_43_epoch2": 0.7926208651399491, "ENV_Test_accuracy_strategy_17_epoch2": 0.7445553539019963, "ENV_Test_accuracy_strategy_93_epoch2": 0.7828096118299446, "ENV_Test_accuracy_per_mean_strategy_epoch2": 0.7966916485281724, "ENV_Test_accuracy_per_mean_user_epoch2": 0.7878344795873667, "ENV_Test_accuracy_per_mean_user_and_bot_epoch2": 0.8217753308379144, "ENV_Online Simulation_TotalLoss_epoch3": 5.608144098519084, "ENV_Online Simulation_Right action_epoch3": 0.4814921472948831, "ENV_Online Simulation_Probability to choose the right action_epoch3": 0.4816043838684563, "ENV_Online Simulation_Weighted right action_epoch3": 0.999589939100415, "ENV_Online Simulation_Weighted probability to choose the right action:_epoch3": 0.9990644165233313, "ENV_Train_TotalLoss_epoch3": 1084.6305220876757, "ENV_Train_Right action_epoch3": 0.7761734365827067, "ENV_Train_Probability to choose the right action_epoch3": 0.6948938163328345, "ENV_Train_Weighted right action_epoch3": 0.7761734365827067, "ENV_Train_Weighted probability to choose the right action:_epoch3": 0.6948938163328345, "ENV_Test_TotalLoss_epoch3": 232.90226833413672, "ENV_Test_Right action_epoch3": 0.778624, "ENV_Test_Probability to choose the right action_epoch3": 0.7165328896070222, "ENV_Test_Weighted right action_epoch3": 0.8240381311478974, "ENV_Test_Weighted probability to choose the right action:_epoch3": 0.7593289769480472, "ENV_Test_proba_accuracy_epoch3": 0.716532889607023, "ENV_Test_proba_accuracy_strategy_132_epoch3": 0.7616356027924391, "ENV_Test_proba_accuracy_strategy_23_epoch3": 0.7153146079891372, "ENV_Test_proba_accuracy_strategy_107_epoch3": 0.8114426966950619, "ENV_Test_proba_accuracy_strategy_43_epoch3": 0.7250553427177318, "ENV_Test_proba_accuracy_strategy_17_epoch3": 0.6834900568381415, "ENV_Test_proba_accuracy_strategy_93_epoch3": 0.7187409249114733, "ENV_Test_proba_accuracy_per_mean_strategy_epoch3": 0.7359465386573308, "ENV_Test_proba_accuracy_per_mean_user_epoch3": 0.7262255053233234, "ENV_Test_proba_accuracy_per_mean_user_and_bot_epoch3": 0.7593289769480475, "ENV_Test_accuracy_epoch3": 0.778624, "ENV_Test_accuracy_strategy_132_epoch3": 0.8084985835694051, "ENV_Test_accuracy_strategy_23_epoch3": 0.7809015996122152, "ENV_Test_accuracy_strategy_107_epoch3": 0.8702791461412152, "ENV_Test_accuracy_strategy_43_epoch3": 0.789440203562341, "ENV_Test_accuracy_strategy_17_epoch3": 0.7461433756805808, "ENV_Test_accuracy_strategy_93_epoch3": 0.7818853974121996, "ENV_Test_accuracy_per_mean_strategy_epoch3": 0.7961913843296595, "ENV_Test_accuracy_per_mean_user_epoch3": 0.7887827480857231, "ENV_Test_accuracy_per_mean_user_and_bot_epoch3": 0.8240381311478976, "ENV_Online Simulation_TotalLoss_epoch4": 5.939909916038542, "ENV_Online Simulation_Right action_epoch4": 0.4848830652740112, "ENV_Online Simulation_Probability to choose the right action_epoch4": 0.4849922416502241, "ENV_Online Simulation_Weighted right action_epoch4": 0.9995179254169668, "ENV_Online Simulation_Weighted probability to choose the right action:_epoch4": 0.9990816761363069, "ENV_Train_TotalLoss_epoch4": 1128.2874745975507, "ENV_Train_Right action_epoch4": 0.7763100879216114, "ENV_Train_Probability to choose the right action_epoch4": 0.6925532274796116, "ENV_Train_Weighted right action_epoch4": 0.7763100879216114, "ENV_Train_Weighted probability to choose the right action:_epoch4": 0.6925532274796116, "ENV_Test_TotalLoss_epoch4": 234.45909478333382, "ENV_Test_Right action_epoch4": 0.779968, "ENV_Test_Probability to choose the right action_epoch4": 0.7192145936697992, "ENV_Test_Weighted right action_epoch4": 0.8214721555454201, "ENV_Test_Weighted probability to choose the right action:_epoch4": 0.7595785303473463, "ENV_Test_proba_accuracy_epoch4": 0.7192145936697988, "ENV_Test_proba_accuracy_strategy_132_epoch4": 0.7567251189181254, "ENV_Test_proba_accuracy_strategy_23_epoch4": 0.7204993419358111, "ENV_Test_proba_accuracy_strategy_107_epoch4": 0.8128074496688822, "ENV_Test_proba_accuracy_strategy_43_epoch4": 0.7261762271124043, "ENV_Test_proba_accuracy_strategy_17_epoch4": 0.6864430102941323, "ENV_Test_proba_accuracy_strategy_93_epoch4": 0.7213939082382591, "ENV_Test_proba_accuracy_per_mean_strategy_epoch4": 0.7373408426946023, "ENV_Test_proba_accuracy_per_mean_user_epoch4": 0.7282789677792826, "ENV_Test_proba_accuracy_per_mean_user_and_bot_epoch4": 0.7595785303473473, "ENV_Test_accuracy_epoch4": 0.779968, "ENV_Test_accuracy_strategy_132_epoch4": 0.8011331444759207, "ENV_Test_accuracy_strategy_23_epoch4": 0.7834868314751979, "ENV_Test_accuracy_strategy_107_epoch4": 0.8686371100164204, "ENV_Test_accuracy_strategy_43_epoch4": 0.7919847328244275, "ENV_Test_accuracy_strategy_17_epoch4": 0.7490925589836661, "ENV_Test_accuracy_strategy_93_epoch4": 0.7837338262476895, "ENV_Test_accuracy_per_mean_strategy_epoch4": 0.7963447006705536, "ENV_Test_accuracy_per_mean_user_epoch4": 0.7889703570212705, "ENV_Test_accuracy_per_mean_user_and_bot_epoch4": 0.8214721555454207, "ENV_Online Simulation_TotalLoss_epoch5": 4.698897840125506, "ENV_Online Simulation_Right action_epoch5": 0.4802206314439874, "ENV_Online Simulation_Probability to choose the right action_epoch5": 0.4803315985632992, "ENV_Online Simulation_Weighted right action_epoch5": 0.9996939343350028, "ENV_Online Simulation_Weighted probability to choose the right action:_epoch5": 0.9992453653973477, "ENV_Train_TotalLoss_epoch5": 1081.7147122655697, "ENV_Train_Right action_epoch5": 0.778442444233242, "ENV_Train_Probability to choose the right action_epoch5": 0.696439516447525, "ENV_Train_Weighted right action_epoch5": 0.778442444233242, "ENV_Train_Weighted probability to choose the right action:_epoch5": 0.696439516447525, "ENV_Test_TotalLoss_epoch5": 233.52615097589003, "ENV_Test_Right action_epoch5": 0.782528, "ENV_Test_Probability to choose the right action_epoch5": 0.7160124026857482, "ENV_Test_Weighted right action_epoch5": 0.8272659882738934, "ENV_Test_Weighted probability to choose the right action:_epoch5": 0.7579114420185872, "ENV_Test_proba_accuracy_epoch5": 0.7160124026857481, "ENV_Test_proba_accuracy_strategy_132_epoch5": 0.7590569343988868, "ENV_Test_proba_accuracy_strategy_23_epoch5": 0.7162969329246612, "ENV_Test_proba_accuracy_strategy_107_epoch5": 0.8077807948841689, "ENV_Test_proba_accuracy_strategy_43_epoch5": 0.7225015306443724, "ENV_Test_proba_accuracy_strategy_17_epoch5": 0.6832001568753949, "ENV_Test_proba_accuracy_strategy_93_epoch5": 0.7167646794047099, "ENV_Test_proba_accuracy_per_mean_strategy_epoch5": 0.7342668381886989, "ENV_Test_proba_accuracy_per_mean_user_epoch5": 0.7254781377894933, "ENV_Test_proba_accuracy_per_mean_user_and_bot_epoch5": 0.7579114420185877, "ENV_Test_accuracy_epoch5": 0.782528, "ENV_Test_accuracy_strategy_132_epoch5": 0.8118980169971671, "ENV_Test_accuracy_strategy_23_epoch5": 0.7844562934238164, "ENV_Test_accuracy_strategy_107_epoch5": 0.8768472906403941, "ENV_Test_accuracy_strategy_43_epoch5": 0.7888040712468194, "ENV_Test_accuracy_strategy_17_epoch5": 0.7520417422867514, "ENV_Test_accuracy_strategy_93_epoch5": 0.7855822550831792, "ENV_Test_accuracy_per_mean_strategy_epoch5": 0.7999382782796879, "ENV_Test_accuracy_per_mean_user_epoch5": 0.7932887809480471, "ENV_Test_accuracy_per_mean_user_and_bot_epoch5": 0.8272659882738933, "ENV_Online Simulation_TotalLoss_epoch6": 6.519518653577404, "ENV_Online Simulation_Right action_epoch6": 0.4865899770996432, "ENV_Online Simulation_Probability to choose the right action_epoch6": 0.48666761347869625, "ENV_Online Simulation_Weighted right action_epoch6": 0.9996385462989331, "ENV_Online Simulation_Weighted probability to choose the right action:_epoch6": 0.9989833354717752, "ENV_Train_TotalLoss_epoch6": 1077.0256299711734, "ENV_Train_Right action_epoch6": 0.7807656291492544, "ENV_Train_Probability to choose the right action_epoch6": 0.6987589150780414, "ENV_Train_Weighted right action_epoch6": 0.7807656291492544, "ENV_Train_Weighted probability to choose the right action:_epoch6": 0.6987589150780414, "ENV_Test_TotalLoss_epoch6": 232.51843449471824, "ENV_Test_Right action_epoch6": 0.779392, "ENV_Test_Probability to choose the right action_epoch6": 0.7118634396763968, "ENV_Test_Weighted right action_epoch6": 0.8244799549148041, "ENV_Test_Weighted probability to choose the right action:_epoch6": 0.7513072541072853, "ENV_Test_proba_accuracy_epoch6": 0.7118634396763968, "ENV_Test_proba_accuracy_strategy_132_epoch6": 0.7518924867046666, "ENV_Test_proba_accuracy_strategy_23_epoch6": 0.713907916593903, "ENV_Test_proba_accuracy_strategy_107_epoch6": 0.8015170672053401, "ENV_Test_proba_accuracy_strategy_43_epoch6": 0.7168489752977035, "ENV_Test_proba_accuracy_strategy_17_epoch6": 0.6784960293657196, "ENV_Test_proba_accuracy_strategy_93_epoch6": 0.7131043711369349, "ENV_Test_proba_accuracy_per_mean_strategy_epoch6": 0.7292944743840447, "ENV_Test_proba_accuracy_per_mean_user_epoch6": 0.7204770507286098, "ENV_Test_proba_accuracy_per_mean_user_and_bot_epoch6": 0.7513072541072848, "ENV_Test_accuracy_epoch6": 0.779392, "ENV_Test_accuracy_strategy_132_epoch6": 0.8084985835694051, "ENV_Test_accuracy_strategy_23_epoch6": 0.7821942155437066, "ENV_Test_accuracy_strategy_107_epoch6": 0.8752052545155994, "ENV_Test_accuracy_strategy_43_epoch6": 0.7888040712468194, "ENV_Test_accuracy_strategy_17_epoch6": 0.7470508166969148, "ENV_Test_accuracy_strategy_93_epoch6": 0.7800369685767098, "ENV_Test_accuracy_per_mean_strategy_epoch6": 0.7969649850248591, "ENV_Test_accuracy_per_mean_user_epoch6": 0.791368292309917, "ENV_Test_accuracy_per_mean_user_and_bot_epoch6": 0.8244799549148044, "ENV_Online Simulation_TotalLoss_epoch7": 6.850172529671176, "ENV_Online Simulation_Right action_epoch7": 0.4817195458404075, "ENV_Online Simulation_Probability to choose the right action_epoch7": 0.48197553657769737, "ENV_Online Simulation_Weighted right action_epoch7": 0.9995592213645405, "ENV_Online Simulation_Weighted probability to choose the right action:_epoch7": 0.9988769704279202, "ENV_Train_TotalLoss_epoch7": 1075.7914869117874, "ENV_Train_Right action_epoch7": 0.781584133506646, "ENV_Train_Probability to choose the right action_epoch7": 0.7005715703743779, "ENV_Train_Weighted right action_epoch7": 0.781584133506646, "ENV_Train_Weighted probability to choose the right action:_epoch7": 0.7005715703743779, "ENV_Test_TotalLoss_epoch7": 234.6114634703648, "ENV_Test_Right action_epoch7": 0.781376, "ENV_Test_Probability to choose the right action_epoch7": 0.7247982258201894, "ENV_Test_Weighted right action_epoch7": 0.8277043838350403, "ENV_Test_Weighted probability to choose the right action:_epoch7": 0.766579972480573, "ENV_Test_proba_accuracy_epoch7": 0.7247982258201896, "ENV_Test_proba_accuracy_strategy_132_epoch7": 0.7648213067807696, "ENV_Test_proba_accuracy_strategy_23_epoch7": 0.726825699142585, "ENV_Test_proba_accuracy_strategy_107_epoch7": 0.8149378827993368, "ENV_Test_proba_accuracy_strategy_43_epoch7": 0.7291543912294259, "ENV_Test_proba_accuracy_strategy_17_epoch7": 0.6919569043066929, "ENV_Test_proba_accuracy_strategy_93_epoch7": 0.7246437265781785, "ENV_Test_proba_accuracy_per_mean_strategy_epoch7": 0.7420566518061649, "ENV_Test_proba_accuracy_per_mean_user_epoch7": 0.7341368705124164, "ENV_Test_proba_accuracy_per_mean_user_and_bot_epoch7": 0.7665799724805727, "ENV_Test_accuracy_epoch7": 0.781376, "ENV_Test_accuracy_strategy_132_epoch7": 0.8118980169971671, "ENV_Test_accuracy_strategy_23_epoch7": 0.7860720633381807, "ENV_Test_accuracy_strategy_107_epoch7": 0.8752052545155994, "ENV_Test_accuracy_strategy_43_epoch7": 0.7888040712468194, "ENV_Test_accuracy_strategy_17_epoch7": 0.7477313974591652, "ENV_Test_accuracy_strategy_93_epoch7": 0.7781885397412199, "ENV_Test_accuracy_per_mean_strategy_epoch7": 0.7979832238830253, "ENV_Test_accuracy_per_mean_user_epoch7": 0.7922709913949451, "ENV_Test_accuracy_per_mean_user_and_bot_epoch7": 0.8277043838350407, "ENV_Online Simulation_TotalLoss_epoch8": 7.118251714038911, "ENV_Online Simulation_Right action_epoch8": 0.4812809206280921, "ENV_Online Simulation_Probability to choose the right action_epoch8": 0.48143512884559725, "ENV_Online Simulation_Weighted right action_epoch8": 0.999412883023932, "ENV_Online Simulation_Weighted probability to choose the right action:_epoch8": 0.9988509428110357, "ENV_Train_TotalLoss_epoch8": 1053.7638590142742, "ENV_Train_Right action_epoch8": 0.7828517912805244, "ENV_Train_Probability to choose the right action_epoch8": 0.70342207795092, "ENV_Train_Weighted right action_epoch8": 0.7828517912805244, "ENV_Train_Weighted probability to choose the right action:_epoch8": 0.70342207795092, "ENV_Test_TotalLoss_epoch8": 232.30554235370485, "ENV_Test_Right action_epoch8": 0.782144, "ENV_Test_Probability to choose the right action_epoch8": 0.7139459854525299, "ENV_Test_Weighted right action_epoch8": 0.8280821515203031, "ENV_Test_Weighted probability to choose the right action:_epoch8": 0.7543071575337658, "ENV_Test_proba_accuracy_epoch8": 0.7139459854525289, "ENV_Test_proba_accuracy_strategy_132_epoch8": 0.7551624438276047, "ENV_Test_proba_accuracy_strategy_23_epoch8": 0.7152128603715376, "ENV_Test_proba_accuracy_strategy_107_epoch8": 0.8026581456903341, "ENV_Test_proba_accuracy_strategy_43_epoch8": 0.7185491487423012, "ENV_Test_proba_accuracy_strategy_17_epoch8": 0.6813139462890223, "ENV_Test_proba_accuracy_strategy_93_epoch8": 0.7157874017655026, "ENV_Test_proba_accuracy_per_mean_strategy_epoch8": 0.7314473244477172, "ENV_Test_proba_accuracy_per_mean_user_epoch8": 0.7229747967972369, "ENV_Test_proba_accuracy_per_mean_user_and_bot_epoch8": 0.7543071575337666, "ENV_Test_accuracy_epoch8": 0.782144, "ENV_Test_accuracy_strategy_132_epoch8": 0.8186968838526912, "ENV_Test_accuracy_strategy_23_epoch8": 0.7846178704152529, "ENV_Test_accuracy_strategy_107_epoch8": 0.8752052545155994, "ENV_Test_accuracy_strategy_43_epoch8": 0.789440203562341, "ENV_Test_accuracy_strategy_17_epoch8": 0.7502268602540835, "ENV_Test_accuracy_strategy_93_epoch8": 0.7754158964879853, "ENV_Test_accuracy_per_mean_strategy_epoch8": 0.7989338281813256, "ENV_Test_accuracy_per_mean_user_epoch8": 0.7935101001536177, "ENV_Test_accuracy_per_mean_user_and_bot_epoch8": 0.828082151520304, "ENV_Online Simulation_TotalLoss_epoch9": 7.374872461732205, "ENV_Online Simulation_Right action_epoch9": 0.47872965038697624, "ENV_Online Simulation_Probability to choose the right action_epoch9": 0.4789412346990458, "ENV_Online Simulation_Weighted right action_epoch9": 0.9995034784403645, "ENV_Online Simulation_Weighted probability to choose the right action:_epoch9": 0.9987527955475267, "ENV_Train_TotalLoss_epoch9": 1057.1649708036623, "ENV_Train_Right action_epoch9": 0.7838374238273607, "ENV_Train_Probability to choose the right action_epoch9": 0.7040390410211305, "ENV_Train_Weighted right action_epoch9": 0.7838374238273607, "ENV_Train_Weighted probability to choose the right action:_epoch9": 0.7040390410211305, "ENV_Test_TotalLoss_epoch9": 230.86857865084636, "ENV_Test_Right action_epoch9": 0.7808, "ENV_Test_Probability to choose the right action_epoch9": 0.7138333924641925, "ENV_Test_Weighted right action_epoch9": 0.8244743823223752, "ENV_Test_Weighted probability to choose the right action:_epoch9": 0.7537156146649545, "ENV_Test_proba_accuracy_epoch9": 0.7138333924641928, "ENV_Test_proba_accuracy_strategy_132_epoch9": 0.7556860456805664, "ENV_Test_proba_accuracy_strategy_23_epoch9": 0.7147379327944893, "ENV_Test_proba_accuracy_strategy_107_epoch9": 0.8048678063727497, "ENV_Test_proba_accuracy_strategy_43_epoch9": 0.71930927267595, "ENV_Test_proba_accuracy_strategy_17_epoch9": 0.6808771130627392, "ENV_Test_proba_accuracy_strategy_93_epoch9": 0.7154554856317599, "ENV_Test_proba_accuracy_per_mean_strategy_epoch9": 0.7318222760363757, "ENV_Test_proba_accuracy_per_mean_user_epoch9": 0.7225315839596654, "ENV_Test_proba_accuracy_per_mean_user_and_bot_epoch9": 0.7537156146649548, "ENV_Test_accuracy_epoch9": 0.7808, "ENV_Test_accuracy_strategy_132_epoch9": 0.8152974504249292, "ENV_Test_accuracy_strategy_23_epoch9": 0.7846178704152529, "ENV_Test_accuracy_strategy_107_epoch9": 0.8768472906403941, "ENV_Test_accuracy_strategy_43_epoch9": 0.7881679389312977, "ENV_Test_accuracy_strategy_17_epoch9": 0.7465970961887477, "ENV_Test_accuracy_strategy_93_epoch9": 0.777264325323475, "ENV_Test_accuracy_per_mean_strategy_epoch9": 0.7981319953206828, "ENV_Test_accuracy_per_mean_user_epoch9": 0.7921987000695457, "ENV_Test_accuracy_per_mean_user_and_bot_epoch9": 0.824474382322376, "_wandb": {"runtime": 3364}}